pyvmlib/__init__.py
pyvmlib-2.4.1.dist-info/LICENSE
pyvmlib-2.4.1.dist-info/METADATA
pyvmlib-2.4.1.dist-info/WHEEL
pyvmlib-2.4.1.dist-info/top_level.txt
pyvmlib-2.4.1.dist-info/RECORD
