Metadata-Version: 2.1
Name: pyvmlib
Version: 2.4.1
Summary: A simple library for controlling VMware vSphere servers.
Home-page: http://github.com/cambridgeconsultants/pyvmlib
Author: Cambridge Consultants
Author-email: vicky.larmour@cambridgeconsultants.com
License: Apache-2.0
Keywords: pyvmlib,pyvmomi,vsphere,vmware,esxi
Platform: UNKNOWN
Classifier: Intended Audience :: Information Technology
Classifier: Intended Audience :: System Administrators
Classifier: Intended Audience :: Developers
Classifier: Environment :: No Input/Output (Daemon)
Classifier: Programming Language :: Python :: 2.7
Classifier: Programming Language :: Python :: 3.4
Classifier: Programming Language :: Python :: 3.5
Classifier: Programming Language :: Python :: 3.6
Classifier: Programming Language :: Python :: 3.7
Classifier: Programming Language :: Python :: 3.8
Classifier: Programming Language :: Python :: 3.9
Classifier: Topic :: Software Development :: Libraries :: Python Modules
Classifier: Topic :: System :: Distributed Computing
Requires-Python: >=2.7, !=3.0.*, !=3.1.*, !=3.2.*, !=3.3.*
License-File: LICENSE
Requires-Dist: pyvmomi
Requires-Dist: requests
Requires-Dist: six
